phy_std_base_toknzer/__init__.py
phy_std_base_toknzer/_tokenize/_token.h
phy_std_base_toknzer/_tokenize/_tokenize.c
phy_std_base_toknzer/_tokenize/_tokenize.h
phy_std_base_toknzer/_tokenize/_tokenize_module.c
phy_std_base_toknzer/_tokenize/lexer/buffer.c
phy_std_base_toknzer/_tokenize/lexer/buffer.h
phy_std_base_toknzer/_tokenize/lexer/lexer.c
phy_std_base_toknzer/_tokenize/lexer/lexer.h
phy_std_base_toknzer/_tokenize/lexer/state.c
phy_std_base_toknzer/_tokenize/lexer/state.h
phy_std_base_toknzer/_tokenize/tokenizer/helpers.c
phy_std_base_toknzer/_tokenize/tokenizer/helpers.h
phy_std_base_toknzer/_tokenize/tokenizer/readline_tokenizer.c
phy_std_base_toknzer/_tokenize/tokenizer/string_tokenizer.c
phy_std_base_toknzer/_tokenize/tokenizer/tokenizer.h
phy_std_base_toknzer/_tokenize/tokenizer/utf8_tokenizer.c
phy_std_base_toknzer/_tokenize.pyd
phy_std_base_toknzer/_tokenize.pyi
phy_std_base_toknzer/tok_def.py
phy_std_base_toknzer-0.1.5.dist-info/METADATA
phy_std_base_toknzer-0.1.5.dist-info/WHEEL
phy_std_base_toknzer-0.1.5.dist-info/RECORD
