Metadata-Version: 2.2
Name: phy-std-base-toknzer
Version: 0.1.5
Summary: Base tokenizer for phy project extracted from python 3.14 builtin tokenize module
Author-Email: alfred-du <ihearmywords@hotmail.com>
Classifier: Programming Language :: Python :: 3
Classifier: Programming Language :: Python :: 3.10
Classifier: Programming Language :: Python :: 3.11
Classifier: Programming Language :: Python :: 3.12
Classifier: Programming Language :: Python :: 3.13
Classifier: Programming Language :: Python :: 3.14
Project-URL: Homepage, https://github.com/phy-precompiler/std-base-toknzer
Project-URL: Repository, https://github.com/phy-precompiler/std-base-toknzer
Project-URL: Issues, https://github.com/phy-precompiler/std-base-toknze/issues
Requires-Python: <4,>=3.10
